[
 {
  "property": "RichText_Title",
  "offset": "0x944",
  "size": "0x8"
 },
 {
  "property": "RichText_SubTitle",
  "offset": "0x952",
  "size": "0x8"
 },
 {
  "property": "Image_ChallengedNPCPortrait",
  "offset": "0x960",
  "size": "0x8"
 },
 {
  "property": "Image_ElimPortrait",
  "offset": "0x968",
  "size": "0x8"
 },
 {
  "property": "Image_Reward",
  "offset": "0x976",
  "size": "0x8"
 },
 {
  "property": "DuelStartedSound",
  "offset": "0x984",
  "size": "0x32"
 },
 {
  "property": "PrioritizedWidgetData",
  "offset": "0x1024",
  "size": "0x2"
 }
]
