[
 {
  "property": "QuestTagToLocationDataTables",
  "offset": "0x48",
  "size": "0x80"
 },
 {
  "property": "FallbackLocationDataTable",
  "offset": "0x128",
  "size": "0x8"
 },
 {
  "property": "DefaultQuestIcon",
  "offset": "0x136",
  "size": "0x32"
 },
 {
  "property": "QuestTagToIconDataTable",
  "offset": "0x168",
  "size": "0x8"
 },
 {
  "property": "DefaultMapMarkerMaterial",
  "offset": "0x176",
  "size": "0x32"
 },
 {
  "property": "QuestTagToCategoryDataTable",
  "offset": "0x208",
  "size": "0x8"
 },
 {
  "property": "CaptureCameraName",
  "offset": "0x216",
  "size": "0x4"
 },
 {
  "property": "CaptureCameraData",
  "offset": "0x224",
  "size": "0x32"
 },
 {
  "property": "CaptureCameraMap",
  "offset": "0x256",
  "size": "0x80"
 },
 {
  "property": "ChallengeMapPoiData",
  "offset": "0x336",
  "size": "0x16"
 },
 {
  "property": "ChallengeMapsPoiData",
  "offset": "0x352",
  "size": "0x80"
 },
 {
  "property": "ProductTagToMapName",
  "offset": "0x432",
  "size": "0x80"
 },
 {
  "property": "RotatedMapProductTags",
  "offset": "0x512",
  "size": "0x80"
 },
 {
  "property": "MapsUIData",
  "offset": "0x592",
  "size": "0x80"
 }
]
